django_admin_caching/__init__.py
django_admin_caching/admin_row.py
django_admin_caching/apps.py
django_admin_caching/caching.py
django_admin_caching/models.py
django_admin_caching/patching.py
django_admin_caching/signals.py
django_admin_caching-0.1.8.dist-info/DESCRIPTION.rst
django_admin_caching-0.1.8.dist-info/METADATA
django_admin_caching-0.1.8.dist-info/RECORD
django_admin_caching-0.1.8.dist-info/WHEEL
django_admin_caching-0.1.8.dist-info/metadata.json
django_admin_caching-0.1.8.dist-info/top_level.txt
