Metadata-Version: 2.0
Name: django-admin-caching
Version: 0.1.8
Summary: Django Admin caching made easy
Home-page: https://github.com/PaesslerAG/django-admin-caching
Author: Paessler AG
Author-email: bis@paessler.com
License: BSD
Keywords: Django,admin,caching
Platform: UNKNOWN
Classifier: Development Status :: 3 - Alpha
Classifier: Intended Audience :: Developers
Classifier: License :: OSI Approved :: BSD License
Classifier: Natural Language :: English
Classifier: Programming Language :: Python :: 2
Classifier: Programming Language :: Python :: 2.7
Classifier: Programming Language :: Python :: 3
Classifier: Programming Language :: Python :: 3.5
Classifier: Programming Language :: Python :: 3.6
Classifier: Framework :: Django
Classifier: Framework :: Django :: 1.11
Classifier: Framework :: Django :: 2.0
Classifier: Framework :: Django :: 2.1
Requires-Dist: Django (<2.2,>=1.8)
